src/__init__.py
src/cli.py
src/config.py
src/config_loader.py
src/logging_config.py
src/ad/__init__.py
src/ad/ad_core.py
src/ad/api.py
src/ad/constraint_jacobian.py
src/ad/derivative_rules.py
src/ad/evaluator.py
src/ad/gradient.py
src/ad/index_mapping.py
src/ad/jacobian.py
src/ad/minmax_flattener.py
src/ad/sparsity.py
src/ad/term_collection.py
src/ad/validation.py
src/diagnostics/__init__.py
src/diagnostics/matrix_market.py
src/diagnostics/statistics.py
src/diagnostics/convexity/__init__.py
src/diagnostics/convexity/pattern_matcher.py
src/diagnostics/convexity/patterns.py
src/emit/__init__.py
src/emit/emit_gams.py
src/emit/equations.py
src/emit/expr_to_gams.py
src/emit/model.py
src/emit/original_symbols.py
src/emit/templates.py
src/gams/__init__.py
src/gams/gams_grammar.lark
src/ir/__init__.py
src/ir/ast.py
src/ir/condition_eval.py
src/ir/minmax_detection.py
src/ir/model_ir.py
src/ir/normalize.py
src/ir/parser.py
src/ir/preprocessor.py
src/ir/symbols.py
src/kkt/__init__.py
src/kkt/assemble.py
src/kkt/complementarity.py
src/kkt/kkt_system.py
src/kkt/naming.py
src/kkt/objective.py
src/kkt/partition.py
src/kkt/reformulation.py
src/kkt/scaling.py
src/kkt/stationarity.py
src/utils/__init__.py
src/utils/error_codes.py
src/utils/error_formatter.py
src/utils/errors.py
src/validation/__init__.py
src/validation/gams_check.py
src/validation/model.py
src/validation/numerical.py
nlp2mcp-0.7.0.dist-info/METADATA
nlp2mcp-0.7.0.dist-info/WHEEL
nlp2mcp-0.7.0.dist-info/entry_points.txt
nlp2mcp-0.7.0.dist-info/top_level.txt
nlp2mcp-0.7.0.dist-info/RECORD
